{"cameraMode":{"drawMode":0,"name":"Shaded","section":"Shading Mode"},"sceneLighting":true,"audioPlay":false,"sceneViewState":{"m_AlwaysRefresh":false,"showFog":true,"showSkybox":true,"showFlares":true,"showImageEffects":true,"showParticleSystems":true,"showVisualEffectGraphs":true,"m_FxEnabled":true},"in2DMode":false,"pivot":{"x":9.522431373596192,"y":-0.5453755855560303,"z":-8.593055725097657},"rotation":{"x":-0.12032733857631684,"y":-0.5286315083503723,"z":0.07601211965084076,"w":-0.8368406295776367},"size":6.451324939727783,"orthographic":false}